BUGS
MANIFEST.in
README.md
pyproject.toml
setup.cfg
bin/configleecher
bin/leechtorrents
bin/uploadtorrents
default/leechtorrents
desktop/uploadtorrents.desktop
doc/bitcoin.png
service/leechtorrents@.service
src/seedboxtools/__init__.py
src/seedboxtools/cli.py
src/seedboxtools/clients.py
src/seedboxtools/config.py
src/seedboxtools/leecher.py
src/seedboxtools/test_util.py
src/seedboxtools/uploader.py
src/seedboxtools/util.py
src/seedboxtools.egg-info/PKG-INFO
src/seedboxtools.egg-info/SOURCES.txt
src/seedboxtools.egg-info/dependency_links.txt
src/seedboxtools.egg-info/requires.txt
src/seedboxtools.egg-info/top_level.txt