Metadata-Version: 2.1
Name: seedboxtools
Version: 1.6.2
Summary: A tool to automate downloading finished torrents from a seedbox
Home-page: https://github.com/Rudd-O/seedboxtools
Author: Manuel Amador (Rudd-O)
Author-email: rudd-o@rudd-o.com
Keywords: seedbox,TorrentFlux,Transmission,PulsedMedia,torrents,download
Classifier: Programming Language :: Python :: 3 :: Only
Classifier: Development Status :: 5 - Production/Stable
Classifier: Environment :: Console
Classifier: Environment :: No Input/Output (Daemon)
Classifier: Intended Audience :: End Users/Desktop
Classifier: Intended Audience :: System Administrators
Classifier: License :: OSI Approved :: GNU Lesser General Public License v2 (LGPLv2)
Classifier: License :: OSI Approved :: GNU General Public License (GPL)
Classifier: Operating System :: POSIX :: Linux
Classifier: Topic :: Communications :: File Sharing
Classifier: Topic :: Utilities
